wav_autoencoder/__init__.py
wav_autoencoder/train.py
wav_autoencoder/utils.py
wav_autoencoder/wavautoencoder.py
wav_autoencoder-0.0.2.dist-info/LICENSE
wav_autoencoder-0.0.2.dist-info/METADATA
wav_autoencoder-0.0.2.dist-info/WHEEL
wav_autoencoder-0.0.2.dist-info/top_level.txt
wav_autoencoder-0.0.2.dist-info/RECORD
