Metadata-Version: 2.1
Name: wav-autoencoder
Version: 0.0.2
Summary: WavAutoencoder: A Self-Supervised Framework for Learning Audio Representations
Home-page: https://github.com/abdouaziz/wolof
Author: Abdou Aziz DIOP
Author-email: abdouaziz@gmail.com
Project-URL: Bug Tracker, https://github.com/abdouaziz/wolof/issues
Classifier: Programming Language :: Python :: 3
Classifier: License :: OSI Approved :: MIT License
Classifier: Operating System :: OS Independent
Requires-Python: >=3.6
License-File: LICENSE
Requires-Dist: datasets
Requires-Dist: librosa
Requires-Dist: torch
Requires-Dist: transformers
